odoo8_addon_account_invoice_reference-8.0.1.0.1.99.dev14-py2.7-nspkg.pth
odoo8_addon_account_invoice_reference-8.0.1.0.1.99.dev14.dist-info/METADATA
odoo8_addon_account_invoice_reference-8.0.1.0.1.99.dev14.dist-info/RECORD
odoo8_addon_account_invoice_reference-8.0.1.0.1.99.dev14.dist-info/WHEEL
odoo8_addon_account_invoice_reference-8.0.1.0.1.99.dev14.dist-info/namespace_packages.txt
odoo8_addon_account_invoice_reference-8.0.1.0.1.99.dev14.dist-info/top_level.txt
odoo_addons/account_invoice_reference/__init__.py
odoo_addons/account_invoice_reference/__openerp__.py
odoo_addons/account_invoice_reference/account_invoice.py
odoo_addons/account_invoice_reference/account_invoice_view.xml
odoo_addons/account_invoice_reference/account_move.py
odoo_addons/account_invoice_reference/i18n/account_invoice_reference.pot
odoo_addons/account_invoice_reference/i18n/am.po
odoo_addons/account_invoice_reference/i18n/ar.po
odoo_addons/account_invoice_reference/i18n/bg.po
odoo_addons/account_invoice_reference/i18n/bs.po
odoo_addons/account_invoice_reference/i18n/ca.po
odoo_addons/account_invoice_reference/i18n/cs.po
odoo_addons/account_invoice_reference/i18n/de.po
odoo_addons/account_invoice_reference/i18n/el_GR.po
odoo_addons/account_invoice_reference/i18n/en_GB.po
odoo_addons/account_invoice_reference/i18n/es.po
odoo_addons/account_invoice_reference/i18n/es_CR.po
odoo_addons/account_invoice_reference/i18n/es_EC.po
odoo_addons/account_invoice_reference/i18n/es_MX.po
odoo_addons/account_invoice_reference/i18n/es_PE.po
odoo_addons/account_invoice_reference/i18n/et.po
odoo_addons/account_invoice_reference/i18n/fi.po
odoo_addons/account_invoice_reference/i18n/fr.po
odoo_addons/account_invoice_reference/i18n/fr_CA.po
odoo_addons/account_invoice_reference/i18n/fr_CH.po
odoo_addons/account_invoice_reference/i18n/gl.po
odoo_addons/account_invoice_reference/i18n/hr.po
odoo_addons/account_invoice_reference/i18n/hr_HR.po
odoo_addons/account_invoice_reference/i18n/hu.po
odoo_addons/account_invoice_reference/i18n/id.po
odoo_addons/account_invoice_reference/i18n/it.po
odoo_addons/account_invoice_reference/i18n/ja.po
odoo_addons/account_invoice_reference/i18n/lt.po
odoo_addons/account_invoice_reference/i18n/mk.po
odoo_addons/account_invoice_reference/i18n/mn.po
odoo_addons/account_invoice_reference/i18n/nb.po
